livesplit/__init__.py
livesplit/client.py
livesplit-1.0.dist-info/LICENSE
livesplit-1.0.dist-info/METADATA
livesplit-1.0.dist-info/WHEEL
livesplit-1.0.dist-info/top_level.txt
livesplit-1.0.dist-info/RECORD
