Metadata-Version: 2.1
Name: livesplit
Version: 1.0
Summary: A library to communicate with LiveSplit server from python.
Home-page: https://github.com/valknight/livesplit-python
Author: Vallerie Knight
Author-email: val@valknight.xyz
License: UNKNOWN
Project-URL: Bug Tracker, https://github.com/valknight/livesplit-python/issues
Platform: UNKNOWN
Classifier: Programming Language :: Python :: 3
Classifier: License :: OSI Approved :: MIT License
Classifier: Operating System :: OS Independent
Requires-Python: >=3.6
License-File: LICENSE
